behave_parallel.egg-info/PKG-INFO
behave_parallel.egg-info/SOURCES.txt
behave_parallel.egg-info/dependency_links.txt
behave_parallel.egg-info/entry_points.txt
behave_parallel.egg-info/requires.txt
behave_parallel.egg-info/top_level.txt
django_behave/__init__.py
django_behave/models.py
django_behave/runner.py
django_behave/splinter.steps_library.py
django_behave/tests.py
django_behave/management/__init__.py
django_behave/management/commands/__init__.py
django_behave/management/commands/test_bdd.py
testBook/__init__.py
testBook/settings.py
testBook/urls.py
testBook/wsgi.py
todo/__init__.py
todo/admin.py
todo/behave-parallel.py
todo/list_steps.py
todo/models.py
todo/tests.py
todo/views.py
todo/migrations/__init__.py